data_creator/__init__.py
data_creator/creator.py
data_creator_for_algo_trade_go-0.1.dist-info/METADATA
data_creator_for_algo_trade_go-0.1.dist-info/WHEEL
data_creator_for_algo_trade_go-0.1.dist-info/top_level.txt
data_creator_for_algo_trade_go-0.1.dist-info/RECORD
