Metadata-Version: 2.1
Name: data-creator-for-algo-trade-go
Version: 0.1
Summary: SQL Server bağlantısı ve veri işleme yardımcı sınıfı
Home-page: UNKNOWN
Author: Okan Uregen
License: UNKNOWN
Platform: UNKNOWN
Classifier: Programming Language :: Python :: 3
Requires-Dist: pymssql
Requires-Dist: pandas
